ong_chrome_automation/__init__.py
ong_chrome_automation/exceptions.py
ong_chrome_automation/local_chrome_browser.py
ong_chrome_automation/playwright_copilot.py
ong_chrome_automation-0.1.3.dist-info/METADATA
ong_chrome_automation-0.1.3.dist-info/WHEEL
ong_chrome_automation-0.1.3.dist-info/top_level.txt
ong_chrome_automation-0.1.3.dist-info/RECORD
