Metadata-Version: 2.4
Name: ong_chrome_automation
Version: 0.1.3
Summary: Class to automate Chrome browser tasks using Playwright. It adds a class to deal with Microsoft Copilot
Author: Oscar Neira
Project-URL: Homepage, https://github.com/Oneirag/ong_chrome_automation
Project-URL: Repository, https://github.com/Oneirag/ong_chrome_automation
Classifier: Development Status :: 3 - Alpha
Classifier: Intended Audience :: End Users/Desktop
Classifier: License :: OSI Approved :: MIT License
Classifier: Programming Language :: Python :: 3
Classifier: Programming Language :: Python :: 3.11
Requires-Python: >=3.11
Requires-Dist: playwright
Requires-Dist: wincertstore
Requires-Dist: cryptography
Requires-Dist: lxml
Requires-Dist: html5lib
Requires-Dist: pandas
Requires-Dist: beautifulsoup4
